[{"zipcode":"207","name":"萬里區","full_name":"新北市萬里區","state_name":null,"city_name":"新北市"},{"zipcode":"208","name":"金山區","full_name":"新北市金山區","state_name":null,"city_name":"新北市"},{"zipcode":"220","name":"板橋區","full_name":"新北市板橋區","state_name":null,"city_name":"新北市"},{"zipcode":"221","name":"汐止區","full_name":"新北市汐止區","state_name":null,"city_name":"新北市"},{"zipcode":"222","name":"深坑區","full_name":"新北市深坑區","state_name":null,"city_name":"新北市"},{"zipcode":"223","name":"石碇區","full_name":"新北市石碇區","state_name":null,"city_name":"新北市"},{"zipcode":"224","name":"瑞芳區","full_name":"新北市瑞芳區","state_name":null,"city_name":"新北市"},{"zipcode":"226","name":"平溪區","full_name":"新北市平溪區","state_name":null,"city_name":"新北市"},{"zipcode":"227","name":"雙溪區","full_name":"新北市雙溪區","state_name":null,"city_name":"新北市"},{"zipcode":"228","name":"貢寮區","full_name":"新北市貢寮區","state_name":null,"city_name":"新北市"},{"zipcode":"231","name":"新店區","full_name":"新北市新店區","state_name":null,"city_name":"新北市"},{"zipcode":"232","name":"坪林區","full_name":"新北市坪林區","state_name":null,"city_name":"新北市"},{"zipcode":"233","name":"烏來區","full_name":"新北市烏來區","state_name":null,"city_name":"新北市"},{"zipcode":"234","name":"永和區","full_name":"新北市永和區","state_name":null,"city_name":"新北市"},{"zipcode":"235","name":"中和區","full_name":"新北市中和區","state_name":null,"city_name":"新北市"},{"zipcode":"236","name":"土城區","full_name":"新北市土城區","state_name":null,"city_name":"新北市"},{"zipcode":"237","name":"三峽區","full_name":"新北市三峽區","state_name":null,"city_name":"新北市"},{"zipcode":"238","name":"樹林區","full_name":"新北市樹林區","state_name":null,"city_name":"新北市"},{"zipcode":"239","name":"鶯歌區","full_name":"新北市鶯歌區","state_name":null,"city_name":"新北市"},{"zipcode":"241","name":"三重區","full_name":"新北市三重區","state_name":null,"city_name":"新北市"},{"zipcode":"242","name":"新莊區","full_name":"新北市新莊區","state_name":null,"city_name":"新北市"},{"zipcode":"243","name":"泰山區","full_name":"新北市泰山區","state_name":null,"city_name":"新北市"},{"zipcode":"244","name":"林口區","full_name":"新北市林口區","state_name":null,"city_name":"新北市"},{"zipcode":"247","name":"蘆洲區","full_name":"新北市蘆洲區","state_name":null,"city_name":"新北市"},{"zipcode":"248","name":"五股區","full_name":"新北市五股區","state_name":null,"city_name":"新北市"},{"zipcode":"249","name":"八里區","full_name":"新北市八里區","state_name":null,"city_name":"新北市"},{"zipcode":"251","name":"淡水區","full_name":"新北市淡水區","state_name":null,"city_name":"新北市"},{"zipcode":"252","name":"三芝區","full_name":"新北市三芝區","state_name":null,"city_name":"新北市"},{"zipcode":"253","name":"石門區","full_name":"新北市石門區","state_name":null,"city_name":"新北市"}]