{"bank":{"code":"771","name":"龍潭區農會（農金資訊所屬會員）"},"branches":[{"branch_code":"0012","bank_branch_code":"7710012","address":"桃園市龍潭區東龍路１００號","name":"龍潭區農會"},{"branch_code":"0023","bank_branch_code":"7710023","address":"桃園市龍潭區九龍里中興路４０９號","name":"中興分部"},{"branch_code":"0034","bank_branch_code":"7710034","address":"桃園市龍潭區烏樹林里中豐路４２８號","name":"烏林分部"},{"branch_code":"0045","bank_branch_code":"7710045","address":"桃園市龍潭區高平里中豐路高平段３２０號","name":"高平分部"},{"branch_code":"0056","bank_branch_code":"7710056","address":"桃園市龍潭區聖德里聖亭路八德段２８號","name":"八德分部"}]}