{"id":"AD","area":468.0,"cioc":"AND","flag":"https://restcountries.eu/data/and.svg","gini":null,"name":"Andorra","latlng":[42.5,1.5],"region":"Europe","borders":["FRA","ESP"],"capital":"Andorra la Vella","demonym":"Andorran","languages":[{"name":"Catalan","iso639_1":"ca","iso639_2":"cat","nativeName":"català"}],"subregion":"Southern Europe","timezones":["UTC+01:00"],"alpha2Code":"AD","alpha3Code":"AND","currencies":[{"code":"EUR","name":"Euro","symbol":"€"}],"nativeName":"Andorra","population":78014,"numericCode":"020","altSpellings":["AD","Principality of Andorra","Principat d'Andorra"],"callingCodes":["376"],"translations":{"br":"Andorra","de":"Andorra","es":"Andorra","fa":"آندورا","fr":"Andorre","hr":"Andora","it":"Andorra","ja":"アンドラ","nl":"Andorra","pt":"Andorra"},"regionalBlocs":[],"topLevelDomain":[".ad"]}