{"id":"BZ","area":22966.0,"cioc":"BIZ","flag":"https://restcountries.eu/data/blz.svg","gini":53.1,"name":"Belize","latlng":[17.25,-88.75],"region":"Americas","borders":["GTM","MEX"],"capital":"Belmopan","demonym":"Belizean","languages":[{"name":"English","iso639_1":"en","iso639_2":"eng","nativeName":"English"},{"name":"Spanish","iso639_1":"es","iso639_2":"spa","nativeName":"Español"}],"subregion":"Central America","timezones":["UTC-06:00"],"alpha2Code":"BZ","alpha3Code":"BLZ","currencies":[{"code":"BZD","name":"Belize dollar","symbol":"$"}],"nativeName":"Belize","population":370300,"numericCode":"084","altSpellings":["BZ"],"callingCodes":["501"],"translations":{"br":"Belize","de":"Belize","es":"Belice","fa":"بلیز","fr":"Belize","hr":"Belize","it":"Belize","ja":"ベリーズ","nl":"Belize","pt":"Belize"},"regionalBlocs":[{"name":"Caribbean Community","acronym":"CARICOM","otherNames":["Comunidad del Caribe","Communauté Caribéenne","Caribische Gemeenschap"],"otherAcronyms":[]},{"name":"Central American Integration System","acronym":"CAIS","otherNames":["Sistema de la Integración Centroamericana,"],"otherAcronyms":["SICA"]}],"topLevelDomain":[".bz"]}