{"id":"ID","area":1904569.0,"cioc":"INA","flag":"https://restcountries.eu/data/idn.svg","gini":34.0,"name":"Indonesia","latlng":[-5.0,120.0],"region":"Asia","borders":["TLS","MYS","PNG"],"capital":"Jakarta","demonym":"Indonesian","languages":[{"name":"Indonesian","iso639_1":"id","iso639_2":"ind","nativeName":"Bahasa Indonesia"}],"subregion":"South-Eastern Asia","timezones":["UTC+07:00","UTC+08:00","UTC+09:00"],"alpha2Code":"ID","alpha3Code":"IDN","currencies":[{"code":"IDR","name":"Indonesian rupiah","symbol":"Rp"}],"nativeName":"Indonesia","population":258705000,"numericCode":"360","altSpellings":["ID","Republic of Indonesia","Republik Indonesia"],"callingCodes":["62"],"translations":{"br":"Indonésia","de":"Indonesien","es":"Indonesia","fa":"اندونزی","fr":"Indonésie","hr":"Indonezija","it":"Indonesia","ja":"インドネシア","nl":"Indonesië","pt":"Indonésia"},"regionalBlocs":[{"name":"Association of Southeast Asian Nations","acronym":"ASEAN","otherNames":[],"otherAcronyms":[]}],"topLevelDomain":[".id"]}