{"id":"ML","area":1240192.0,"cioc":"MLI","flag":"https://restcountries.eu/data/mli.svg","gini":33.0,"name":"Mali","latlng":[17.0,-4.0],"region":"Africa","borders":["DZA","BFA","GIN","CIV","MRT","NER","SEN"],"capital":"Bamako","demonym":"Malian","languages":[{"name":"French","iso639_1":"fr","iso639_2":"fra","nativeName":"français"}],"subregion":"Western Africa","timezones":["UTC"],"alpha2Code":"ML","alpha3Code":"MLI","currencies":[{"code":"XOF","name":"West African CFA franc","symbol":"Fr"}],"nativeName":"Mali","population":18135000,"numericCode":"466","altSpellings":["ML","Republic of Mali","République du Mali"],"callingCodes":["223"],"translations":{"br":"Mali","de":"Mali","es":"Mali","fa":"مالی","fr":"Mali","hr":"Mali","it":"Mali","ja":"マリ","nl":"Mali","pt":"Mali"},"regionalBlocs":[{"name":"African Union","acronym":"AU","otherNames":["الاتحاد الأفريقي","Union africaine","União Africana","Unión Africana","Umoja wa Afrika"],"otherAcronyms":[]}],"topLevelDomain":[".ml"]}