{"id":"PA","area":75417.0,"cioc":"PAN","flag":"https://restcountries.eu/data/pan.svg","gini":51.9,"name":"Panama","latlng":[9.0,-80.0],"region":"Americas","borders":["COL","CRI"],"capital":"Panama City","demonym":"Panamanian","languages":[{"name":"Spanish","iso639_1":"es","iso639_2":"spa","nativeName":"Español"}],"subregion":"Central America","timezones":["UTC-05:00"],"alpha2Code":"PA","alpha3Code":"PAN","currencies":[{"code":"PAB","name":"Panamanian balboa","symbol":"B/."},{"code":"USD","name":"United States dollar","symbol":"$"}],"nativeName":"Panamá","population":3814672,"numericCode":"591","altSpellings":["PA","Republic of Panama","República de Panamá"],"callingCodes":["507"],"translations":{"br":"Panamá","de":"Panama","es":"Panamá","fa":"پاناما","fr":"Panama","hr":"Panama","it":"Panama","ja":"パナマ","nl":"Panama","pt":"Panamá"},"regionalBlocs":[{"name":"Central American Integration System","acronym":"CAIS","otherNames":["Sistema de la Integración Centroamericana,"],"otherAcronyms":["SICA"]}],"topLevelDomain":[".pa"]}