{"id":"PR","area":8870.0,"cioc":"PUR","flag":"https://restcountries.eu/data/pri.svg","gini":null,"name":"Puerto Rico","latlng":[18.25,-66.5],"region":"Americas","borders":[],"capital":"San Juan","demonym":"Puerto Rican","languages":[{"name":"Spanish","iso639_1":"es","iso639_2":"spa","nativeName":"Español"},{"name":"English","iso639_1":"en","iso639_2":"eng","nativeName":"English"}],"subregion":"Caribbean","timezones":["UTC-04:00"],"alpha2Code":"PR","alpha3Code":"PRI","currencies":[{"code":"USD","name":"United States dollar","symbol":"$"}],"nativeName":"Puerto Rico","population":3474182,"numericCode":"630","altSpellings":["PR","Commonwealth of Puerto Rico","Estado Libre Asociado de Puerto Rico"],"callingCodes":["1787","1939"],"translations":{"br":"Porto Rico","de":"Puerto Rico","es":"Puerto Rico","fa":"پورتو ریکو","fr":"Porto Rico","hr":"Portoriko","it":"Porto Rico","ja":"プエルトリコ","nl":"Puerto Rico","pt":"Porto Rico"},"regionalBlocs":[],"topLevelDomain":[".pr"]}