{"id":"TT","area":5130.0,"cioc":"TTO","flag":"https://restcountries.eu/data/tto.svg","gini":40.3,"name":"Trinidad and Tobago","latlng":[11.0,-61.0],"region":"Americas","borders":[],"capital":"Port of Spain","demonym":"Trinidadian","languages":[{"name":"English","iso639_1":"en","iso639_2":"eng","nativeName":"English"}],"subregion":"Caribbean","timezones":["UTC-04:00"],"alpha2Code":"TT","alpha3Code":"TTO","currencies":[{"code":"TTD","name":"Trinidad and Tobago dollar","symbol":"$"}],"nativeName":"Trinidad and Tobago","population":1349667,"numericCode":"780","altSpellings":["TT","Republic of Trinidad and Tobago"],"callingCodes":["1868"],"translations":{"br":"Trinidad e Tobago","de":"Trinidad und Tobago","es":"Trinidad y Tobago","fa":"ترینیداد و توباگو","fr":"Trinité et Tobago","hr":"Trinidad i Tobago","it":"Trinidad e Tobago","ja":"トリニダード・トバゴ","nl":"Trinidad en Tobago","pt":"Trindade e Tobago"},"regionalBlocs":[{"name":"Caribbean Community","acronym":"CARICOM","otherNames":["Comunidad del Caribe","Communauté Caribéenne","Caribische Gemeenschap"],"otherAcronyms":[]}],"topLevelDomain":[".tt"]}